primefactors/__init__.py
primefactors/__main__.py
primefactors/formatters.py
primefactors-1.0.0.dist-info/LICENSE
primefactors-1.0.0.dist-info/METADATA
primefactors-1.0.0.dist-info/WHEEL
primefactors-1.0.0.dist-info/top_level.txt
primefactors-1.0.0.dist-info/RECORD
